{
  "nightly": {
    "description": "Every commit to master",
    "hide": false,
    "last_updated": "2025-04-16T20:25:41.000Z",
    "last_updated_url": "https://github.com/hotio/autoscan/actions/runs/14501852512",
    "latest": false,
    "tags": [
      "nightly",
      "nightly-1d41f4b47ede7531ecc24944bfcaf88db10c2ba7",
      "nightly-e6c20a3"
    ]
  },
  "release": {
    "description": "Releases",
    "hide": false,
    "last_updated": "2025-04-16T20:27:05.000Z",
    "last_updated_url": "https://github.com/hotio/autoscan/actions/runs/14501852760",
    "latest": true,
    "tags": [
      "release",
      "release-1.4.0",
      "release-f2d6507"
    ]
  }
}
