{
  "nightly": {
    "commit_message": "Upstream image update",
    "commit_sha": "390d9dec10eeebf5146c3b46134e7b87b29e0ee5",
    "description": "Every commit to master",
    "hide": false,
    "last_updated": "2026-01-04T09:25:18.000Z",
    "last_updated_url": "https://github.com/hotio/autoscan/actions/runs/20690818540",
    "latest": false,
    "tags": [
      "nightly",
      "nightly-1d41f4b47ede7531ecc24944bfcaf88db10c2ba7",
      "nightly-390d9de",
      "",
      "",
      ""
    ]
  },
  "release": {
    "commit_message": "Upstream image update",
    "description": "Releases",
    "hide": false,
    "last_updated": "2026-01-04T09:25:20.000Z",
    "last_updated_url": "https://github.com/hotio/autoscan/actions/runs/20690818826",
    "latest": true,
    "tags": [
      "release",
      "release-1.4.0",
      "release-56804b5",
      "release-v1",
      "release-v1.4",
      "release-v1.4.0"
    ]
  }
}
